league_client/__init__.py
league_client/connection.py
league_client/constants.py
league_client/exceptions.py
league_client/py.typed
league_client/types.py
league_client/utils.py
league_client/lcu/__init__.py
league_client/lcu/craft.py
league_client/lcu/disenchant.py
league_client/lcu/inventory.py
league_client/lcu/lobby.py
league_client/lcu/loot.py
league_client/lcu/match_history.py
league_client/lcu/ranked.py
league_client/lcu/summoner.py
league_client/lcu/username.py
league_client/lcu/wallet.py
league_client/rcu/__init__.py
league_client/rcu/auth.py
league_client/rcu/region_locale.py
league_client/rcu/userinfo.py
league_client/rso/__init__.py
league_client/rso/auth.py
league_client/rso/chat.py
league_client/rso/constants.py
league_client/rso/craft.py
league_client/rso/disenchant.py
league_client/rso/honor.py
league_client/rso/inventory.py
league_client/rso/loot.py
league_client/rso/match.py
league_client/rso/missions.py
league_client/rso/models.py
league_client/rso/party.py
league_client/rso/password.py
league_client/rso/rank.py
league_client/rso/sign_up.py
league_client/rso/skin.py
league_client/rso/userinfo.py
league_client/rso/utils.py
league_client/rso/verifications.py
league_client/shortcuts/__init__.py
league_client/shortcuts/logger.py
league_client/shortcuts/rso.py
league_client-2.1.16.dist-info/LICENSE
league_client-2.1.16.dist-info/METADATA
league_client-2.1.16.dist-info/WHEEL
league_client-2.1.16.dist-info/top_level.txt
league_client-2.1.16.dist-info/RECORD
