Metadata-Version: 2.2
Name: league-client
Version: 2.1.16
Summary: league-client is a python package to communicate with riot servers
Author-email: Pradish Bijukchhe <pradishbijukchhe@gmail.com>
License: Copyright (c) 2018 The Python Packaging Authority
Project-URL: Homepage, https://github.com/sandbox-pokhara/league-client
Project-URL: Issues, https://github.com/sandbox-pokhara/league-client/issues
Classifier: Programming Language :: Python :: 3
Requires-Python: >=3
License-File: LICENSE
Requires-Dist: httpx
Requires-Dist: tenacity
Provides-Extra: lcu
Requires-Dist: psutil; extra == "lcu"
